ci_ver/__init__.py
ci_ver-1.0.1.dist-info/METADATA
ci_ver-1.0.1.dist-info/WHEEL
ci_ver-1.0.1.dist-info/entry_points.txt
ci_ver-1.0.1.dist-info/licenses/LICENSE
ci_ver-1.0.1.dist-info/RECORD
