Metadata-Version: 2.4
Name: ci-ver
Version: 1.0.1
Summary: CI version utility for managing versioning in development branches
Project-URL: Homepage, https://github.com/ruzzz/py-ci-ver
Author-email: Ruslan Zaporojets <ruzzzua@gmail.com>
Maintainer-email: Ruslan Zaporojets <ruzzzua@gmail.com>
License: MIT
License-File: LICENSE
Keywords: utilities,vcs,version
Classifier: License :: OSI Approved :: MIT License
Classifier: Operating System :: OS Independent
Classifier: Programming Language :: Python :: 3.10
Classifier: Topic :: Software Development :: Build Tools
Classifier: Topic :: Software Development :: Testing
Classifier: Topic :: Software Development :: Version Control
Classifier: Topic :: Utilities
Requires-Python: >=3.10
